ptrading/__init__.py
ptrading/config/__init__.py
ptrading/config/_config.py
ptrading/data/__init__.py
ptrading/data/_bar.py
ptrading/data/_data.py
ptrading/signal/__init__.py
ptrading/signal/_basic.py
ptrading/signal/_signal.py
ptrading/simulator/__init__.py
ptrading/simulator/_order.py
ptrading/simulator/_policy.py
ptrading/simulator/_simulator.py
ptrading/simulator/_state.py
ptrading/strategy/__init__.py
ptrading/strategy/_strategy.py
ptrading/utils/__init__.py
ptrading/utils/_buffer.py
ptrading/utils/_time.py
ptrading-0.0.1.0a3.dist-info/LICENSE.md
ptrading-0.0.1.0a3.dist-info/METADATA
ptrading-0.0.1.0a3.dist-info/WHEEL
ptrading-0.0.1.0a3.dist-info/top_level.txt
ptrading-0.0.1.0a3.dist-info/RECORD
